README.rst
cask.py
setup.py
cask.egg-info/PKG-INFO
cask.egg-info/SOURCES.txt
cask.egg-info/dependency_links.txt
cask.egg-info/not-zip-safe
cask.egg-info/requires.txt
cask.egg-info/top_level.txt